acordes/__init__.py
acordes/chord.py
acordes/example.py
acordes/formatting.py
acordes/instruments.py
acordes/note.py
acordes/tuning.py
acordes-1.1.0.dist-info/licenses/LICENSE
acordes-1.1.0.dist-info/METADATA
acordes-1.1.0.dist-info/WHEEL
acordes-1.1.0.dist-info/top_level.txt
acordes-1.1.0.dist-info/RECORD
