Metadata-Version: 2.4
Name: acordes
Version: 1.1.0
Summary: how to play a chord on a stringed instrument
Author-email: Stanislav Syekirin <syekirin@gmail.com>
Project-URL: Homepage, https://codeberg.org/Zabolekar/acordes
Classifier: Programming Language :: Python :: 3
Classifier: License :: OSI Approved :: MIT License
Classifier: Operating System :: OS Independent
Requires-Python: >=3.10
License-File: LICENSE
Requires-Dist: colorama
Dynamic: license-file
